asup/__about__.py
asup/__init__.py
asup/app.py
asup/entrypoint.py
asup/print.py
asup/sample.json
asup/tasks.py
asup/template.html
asup-0.0.21.dist-info/METADATA
asup-0.0.21.dist-info/WHEEL
asup-0.0.21.dist-info/entry_points.txt
asup-0.0.21.dist-info/licenses/LICENSE.txt
asup-0.0.21.dist-info/RECORD
